[
  {
    "index": 1,
    "file": "series_001_A-1.00_fhat-0.250.npz",
    "A_factor": -1.0,
    "fhat": -0.25
  },
  {
    "index": 2,
    "file": "series_002_A-1.00_fhat-0.200.npz",
    "A_factor": -1.0,
    "fhat": -0.2
  },
  {
    "index": 3,
    "file": "series_003_A-1.00_fhat-0.100.npz",
    "A_factor": -1.0,
    "fhat": -0.1
  },
  {
    "index": 4,
    "file": "series_004_A-1.00_fhat-0.050.npz",
    "A_factor": -1.0,
    "fhat": -0.05
  },
  {
    "index": 5,
    "file": "series_005_A-1.00_fhat0.000.npz",
    "A_factor": -1.0,
    "fhat": 0.0
  },
  {
    "index": 6,
    "file": "series_006_A-1.00_fhat0.050.npz",
    "A_factor": -1.0,
    "fhat": 0.05
  },
  {
    "index": 7,
    "file": "series_007_A-1.00_fhat0.100.npz",
    "A_factor": -1.0,
    "fhat": 0.1
  },
  {
    "index": 8,
    "file": "series_008_A-1.00_fhat0.200.npz",
    "A_factor": -1.0,
    "fhat": 0.2
  },
  {
    "index": 9,
    "file": "series_009_A-1.00_fhat0.250.npz",
    "A_factor": -1.0,
    "fhat": 0.25
  },
  {
    "index": 10,
    "file": "series_010_A-0.80_fhat-0.250.npz",
    "A_factor": -0.8,
    "fhat": -0.25
  },
  {
    "index": 11,
    "file": "series_011_A-0.80_fhat-0.200.npz",
    "A_factor": -0.8,
    "fhat": -0.2
  },
  {
    "index": 12,
    "file": "series_012_A-0.80_fhat-0.100.npz",
    "A_factor": -0.8,
    "fhat": -0.1
  },
  {
    "index": 13,
    "file": "series_013_A-0.80_fhat-0.050.npz",
    "A_factor": -0.8,
    "fhat": -0.05
  },
  {
    "index": 14,
    "file": "series_014_A-0.80_fhat0.000.npz",
    "A_factor": -0.8,
    "fhat": 0.0
  },
  {
    "index": 15,
    "file": "series_015_A-0.80_fhat0.050.npz",
    "A_factor": -0.8,
    "fhat": 0.05
  },
  {
    "index": 16,
    "file": "series_016_A-0.80_fhat0.100.npz",
    "A_factor": -0.8,
    "fhat": 0.1
  },
  {
    "index": 17,
    "file": "series_017_A-0.80_fhat0.200.npz",
    "A_factor": -0.8,
    "fhat": 0.2
  },
  {
    "index": 18,
    "file": "series_018_A-0.80_fhat0.250.npz",
    "A_factor": -0.8,
    "fhat": 0.25
  },
  {
    "index": 19,
    "file": "series_019_A-0.40_fhat-0.250.npz",
    "A_factor": -0.4,
    "fhat": -0.25
  },
  {
    "index": 20,
    "file": "series_020_A-0.40_fhat-0.200.npz",
    "A_factor": -0.4,
    "fhat": -0.2
  },
  {
    "index": 21,
    "file": "series_021_A-0.40_fhat-0.100.npz",
    "A_factor": -0.4,
    "fhat": -0.1
  },
  {
    "index": 22,
    "file": "series_022_A-0.40_fhat-0.050.npz",
    "A_factor": -0.4,
    "fhat": -0.05
  },
  {
    "index": 23,
    "file": "series_023_A-0.40_fhat0.000.npz",
    "A_factor": -0.4,
    "fhat": 0.0
  },
  {
    "index": 24,
    "file": "series_024_A-0.40_fhat0.050.npz",
    "A_factor": -0.4,
    "fhat": 0.05
  },
  {
    "index": 25,
    "file": "series_025_A-0.40_fhat0.100.npz",
    "A_factor": -0.4,
    "fhat": 0.1
  },
  {
    "index": 26,
    "file": "series_026_A-0.40_fhat0.200.npz",
    "A_factor": -0.4,
    "fhat": 0.2
  },
  {
    "index": 27,
    "file": "series_027_A-0.40_fhat0.250.npz",
    "A_factor": -0.4,
    "fhat": 0.25
  },
  {
    "index": 28,
    "file": "series_028_A-0.20_fhat-0.250.npz",
    "A_factor": -0.2,
    "fhat": -0.25
  },
  {
    "index": 29,
    "file": "series_029_A-0.20_fhat-0.200.npz",
    "A_factor": -0.2,
    "fhat": -0.2
  },
  {
    "index": 30,
    "file": "series_030_A-0.20_fhat-0.100.npz",
    "A_factor": -0.2,
    "fhat": -0.1
  },
  {
    "index": 31,
    "file": "series_031_A-0.20_fhat-0.050.npz",
    "A_factor": -0.2,
    "fhat": -0.05
  },
  {
    "index": 32,
    "file": "series_032_A-0.20_fhat0.000.npz",
    "A_factor": -0.2,
    "fhat": 0.0
  },
  {
    "index": 33,
    "file": "series_033_A-0.20_fhat0.050.npz",
    "A_factor": -0.2,
    "fhat": 0.05
  },
  {
    "index": 34,
    "file": "series_034_A-0.20_fhat0.100.npz",
    "A_factor": -0.2,
    "fhat": 0.1
  },
  {
    "index": 35,
    "file": "series_035_A-0.20_fhat0.200.npz",
    "A_factor": -0.2,
    "fhat": 0.2
  },
  {
    "index": 36,
    "file": "series_036_A-0.20_fhat0.250.npz",
    "A_factor": -0.2,
    "fhat": 0.25
  },
  {
    "index": 37,
    "file": "series_037_A0.00_fhat-0.250.npz",
    "A_factor": 0.0,
    "fhat": -0.25
  },
  {
    "index": 38,
    "file": "series_038_A0.00_fhat-0.200.npz",
    "A_factor": 0.0,
    "fhat": -0.2
  },
  {
    "index": 39,
    "file": "series_039_A0.00_fhat-0.100.npz",
    "A_factor": 0.0,
    "fhat": -0.1
  },
  {
    "index": 40,
    "file": "series_040_A0.00_fhat-0.050.npz",
    "A_factor": 0.0,
    "fhat": -0.05
  },
  {
    "index": 41,
    "file": "series_041_A0.00_fhat0.000.npz",
    "A_factor": 0.0,
    "fhat": 0.0
  },
  {
    "index": 42,
    "file": "series_042_A0.00_fhat0.050.npz",
    "A_factor": 0.0,
    "fhat": 0.05
  },
  {
    "index": 43,
    "file": "series_043_A0.00_fhat0.100.npz",
    "A_factor": 0.0,
    "fhat": 0.1
  },
  {
    "index": 44,
    "file": "series_044_A0.00_fhat0.200.npz",
    "A_factor": 0.0,
    "fhat": 0.2
  },
  {
    "index": 45,
    "file": "series_045_A0.00_fhat0.250.npz",
    "A_factor": 0.0,
    "fhat": 0.25
  },
  {
    "index": 46,
    "file": "series_046_A0.20_fhat-0.250.npz",
    "A_factor": 0.2,
    "fhat": -0.25
  },
  {
    "index": 47,
    "file": "series_047_A0.20_fhat-0.200.npz",
    "A_factor": 0.2,
    "fhat": -0.2
  },
  {
    "index": 48,
    "file": "series_048_A0.20_fhat-0.100.npz",
    "A_factor": 0.2,
    "fhat": -0.1
  },
  {
    "index": 49,
    "file": "series_049_A0.20_fhat-0.050.npz",
    "A_factor": 0.2,
    "fhat": -0.05
  },
  {
    "index": 50,
    "file": "series_050_A0.20_fhat0.000.npz",
    "A_factor": 0.2,
    "fhat": 0.0
  },
  {
    "index": 51,
    "file": "series_051_A0.20_fhat0.050.npz",
    "A_factor": 0.2,
    "fhat": 0.05
  },
  {
    "index": 52,
    "file": "series_052_A0.20_fhat0.100.npz",
    "A_factor": 0.2,
    "fhat": 0.1
  },
  {
    "index": 53,
    "file": "series_053_A0.20_fhat0.200.npz",
    "A_factor": 0.2,
    "fhat": 0.2
  },
  {
    "index": 54,
    "file": "series_054_A0.20_fhat0.250.npz",
    "A_factor": 0.2,
    "fhat": 0.25
  },
  {
    "index": 55,
    "file": "series_055_A0.40_fhat-0.250.npz",
    "A_factor": 0.4,
    "fhat": -0.25
  },
  {
    "index": 56,
    "file": "series_056_A0.40_fhat-0.200.npz",
    "A_factor": 0.4,
    "fhat": -0.2
  },
  {
    "index": 57,
    "file": "series_057_A0.40_fhat-0.100.npz",
    "A_factor": 0.4,
    "fhat": -0.1
  },
  {
    "index": 58,
    "file": "series_058_A0.40_fhat-0.050.npz",
    "A_factor": 0.4,
    "fhat": -0.05
  },
  {
    "index": 59,
    "file": "series_059_A0.40_fhat0.000.npz",
    "A_factor": 0.4,
    "fhat": 0.0
  },
  {
    "index": 60,
    "file": "series_060_A0.40_fhat0.050.npz",
    "A_factor": 0.4,
    "fhat": 0.05
  },
  {
    "index": 61,
    "file": "series_061_A0.40_fhat0.100.npz",
    "A_factor": 0.4,
    "fhat": 0.1
  },
  {
    "index": 62,
    "file": "series_062_A0.40_fhat0.200.npz",
    "A_factor": 0.4,
    "fhat": 0.2
  },
  {
    "index": 63,
    "file": "series_063_A0.40_fhat0.250.npz",
    "A_factor": 0.4,
    "fhat": 0.25
  },
  {
    "index": 64,
    "file": "series_064_A0.80_fhat-0.250.npz",
    "A_factor": 0.8,
    "fhat": -0.25
  },
  {
    "index": 65,
    "file": "series_065_A0.80_fhat-0.200.npz",
    "A_factor": 0.8,
    "fhat": -0.2
  },
  {
    "index": 66,
    "file": "series_066_A0.80_fhat-0.100.npz",
    "A_factor": 0.8,
    "fhat": -0.1
  },
  {
    "index": 67,
    "file": "series_067_A0.80_fhat-0.050.npz",
    "A_factor": 0.8,
    "fhat": -0.05
  },
  {
    "index": 68,
    "file": "series_068_A0.80_fhat0.000.npz",
    "A_factor": 0.8,
    "fhat": 0.0
  },
  {
    "index": 69,
    "file": "series_069_A0.80_fhat0.050.npz",
    "A_factor": 0.8,
    "fhat": 0.05
  },
  {
    "index": 70,
    "file": "series_070_A0.80_fhat0.100.npz",
    "A_factor": 0.8,
    "fhat": 0.1
  },
  {
    "index": 71,
    "file": "series_071_A0.80_fhat0.200.npz",
    "A_factor": 0.8,
    "fhat": 0.2
  },
  {
    "index": 72,
    "file": "series_072_A0.80_fhat0.250.npz",
    "A_factor": 0.8,
    "fhat": 0.25
  },
  {
    "index": 73,
    "file": "series_073_A1.00_fhat-0.250.npz",
    "A_factor": 1.0,
    "fhat": -0.25
  },
  {
    "index": 74,
    "file": "series_074_A1.00_fhat-0.200.npz",
    "A_factor": 1.0,
    "fhat": -0.2
  },
  {
    "index": 75,
    "file": "series_075_A1.00_fhat-0.100.npz",
    "A_factor": 1.0,
    "fhat": -0.1
  },
  {
    "index": 76,
    "file": "series_076_A1.00_fhat-0.050.npz",
    "A_factor": 1.0,
    "fhat": -0.05
  },
  {
    "index": 77,
    "file": "series_077_A1.00_fhat0.000.npz",
    "A_factor": 1.0,
    "fhat": 0.0
  },
  {
    "index": 78,
    "file": "series_078_A1.00_fhat0.050.npz",
    "A_factor": 1.0,
    "fhat": 0.05
  },
  {
    "index": 79,
    "file": "series_079_A1.00_fhat0.100.npz",
    "A_factor": 1.0,
    "fhat": 0.1
  },
  {
    "index": 80,
    "file": "series_080_A1.00_fhat0.200.npz",
    "A_factor": 1.0,
    "fhat": 0.2
  },
  {
    "index": 81,
    "file": "series_081_A1.00_fhat0.250.npz",
    "A_factor": 1.0,
    "fhat": 0.25
  }
]